buildertron/__init__.py
buildertron/buildertron.png
buildertron/buildertron.py
buildertron/splash.png
buildertron/version.py
buildertron/dialogs/__init__.py
buildertron/dialogs/aboutdialog.py
buildertron/dialogs/androidpermissionsdialog.py
buildertron/dialogs/settingsdialog.py
buildertron/dialogs/submitissuedialog.py
buildertron/forms/__init__.py
buildertron/forms/mainwindow.py
buildertron/forms/uiaboutdialog.py
buildertron/forms/uiandroidpermissionsdialog.py
buildertron/forms/uimainwindow.py
buildertron/forms/uisettingsdialog.py
buildertron/forms/uisubmitissuedialog.py
buildertron/icons/build.png
buildertron/icons/clean.png
buildertron/icons/deploy.png
buildertron/icons/distclean.png
buildertron/icons/new.png
buildertron/icons/open.png
buildertron/icons/run.png
buildertron/icons/save.png
buildertron/icons/saveas.png
buildertron/icons/serve.png
buildertron/icons/terminal.png
buildertron/icons/undo.png
buildertron/spec/__init__.py
buildertron/spec/android_permissions.py
buildertron/spec/android_presplash_colors.py
buildertron/spec/buildozerdefault.py
buildertron/spec/default.py
buildertron/spec/translate_objects.py
buildertron-0.1.0.data/data/share/applications/Buildertron.desktop
buildertron-0.1.0.data/data/share/buildertron/buildertron.png
buildertron-0.1.0.dist-info/DESCRIPTION.rst
buildertron-0.1.0.dist-info/METADATA
buildertron-0.1.0.dist-info/RECORD
buildertron-0.1.0.dist-info/WHEEL
buildertron-0.1.0.dist-info/entry_points.txt
buildertron-0.1.0.dist-info/metadata.json
buildertron-0.1.0.dist-info/top_level.txt
